signal_handler/__init__.py
signal_handler-0.0.5.dist-info/LICENSE
signal_handler-0.0.5.dist-info/METADATA
signal_handler-0.0.5.dist-info/WHEEL
signal_handler-0.0.5.dist-info/top_level.txt
signal_handler-0.0.5.dist-info/RECORD
