Metadata-Version: 2.1
Name: signal_handler
Version: 0.0.5
Summary: Handling system signals and taking actions on application termination
Home-page: https://github.com/oleglpts/signal_handler
Author: Oleg Lupats
Author-email: oleglupats@gmail.com
License: MIT
License-File: LICENSE
